easytwitter/__init__.py
easytwitter/user.py
easytwitter-0.1.2.dist-info/LICENSE
easytwitter-0.1.2.dist-info/METADATA
easytwitter-0.1.2.dist-info/WHEEL
easytwitter-0.1.2.dist-info/top_level.txt
easytwitter-0.1.2.dist-info/RECORD
