Metadata-Version: 2.1
Name: easytwitter
Version: 0.1.2
Summary: Simplifing Twitter APIs.
Home-page: https://github.com/mutairibassam/easy-twitter
Author: mutairibassam
Author-email: mutairibassam@gmail.com
License: MIT
Keywords: twitterapi
Platform: UNKNOWN
Classifier: Development Status :: 4 - Beta
Classifier: Framework :: Jupyter
Classifier: Intended Audience :: Developers
Classifier: Operating System :: MacOS
Classifier: License :: OSI Approved :: MIT License
Classifier: Programming Language :: Python :: 3
Classifier: Topic :: Software Development :: Libraries :: Python Modules
Provides-Extra: dev
Requires-Dist: pytest (>=3.7) ; extra == 'dev'
